setup.py
metadata/__init__.py
metadata.egg-info/PKG-INFO
metadata.egg-info/SOURCES.txt
metadata.egg-info/dependency_links.txt
metadata.egg-info/not-zip-safe
metadata.egg-info/requires.txt
metadata.egg-info/top_level.txt