Metadata-Version: 1.0
Name: metadata
Version: 0.1.1
Summary: Metadata for Humans
Home-page: https://github.com/cyberdelia/metadata
Author: Timothée Peignier
Author-email: timothee.peignier@tryphon.org
License: UNKNOWN
Platform: UNKNOWN
Classifier: Intended Audience :: Developers
Classifier: License :: OSI Approved :: MIT License
Classifier: Operating System :: OS Independent
Classifier: Programming Language :: Python
Classifier: Topic :: Utilities
